README.rst
setup.py
frankfurt/__init__.py
frankfurt/database.py
frankfurt/exceptions.py
frankfurt/fields.py
frankfurt/models.py
frankfurt/sql.py
frankfurt.egg-info/PKG-INFO
frankfurt.egg-info/SOURCES.txt
frankfurt.egg-info/dependency_links.txt
frankfurt.egg-info/requires.txt
frankfurt.egg-info/top_level.txt
tests/__init__.py
tests/conftest.py
tests/test_database.py
tests/test_fields.py
tests/test_inheritance.py
tests/test_models.py
tests/test_sql.py