Metadata-Version: 2.1
Name: frankfurt
Version: 0.1b34
Summary: Frankfurt is an ORM based on asyncpg.
Home-page: https://gitlab.com/jorgeecardona/frankfurt
Author: Jorge E. Cardona
Author-email: jorgeecardona@gmail.com
License: UNKNOWN
Platform: UNKNOWN
Classifier: Programming Language :: Python :: 3
Classifier: License :: OSI Approved :: MIT License
Classifier: Operating System :: OS Independent
Classifier: Framework :: AsyncIO
Classifier: Topic :: Database
Classifier: License :: OSI Approved :: GNU Lesser General Public License v3 or later (LGPLv3+)
Requires-Python: >=3.7
